datasette_init/__init__.py
datasette_init-0.2.dist-info/METADATA
datasette_init-0.2.dist-info/WHEEL
datasette_init-0.2.dist-info/entry_points.txt
datasette_init-0.2.dist-info/top_level.txt
datasette_init-0.2.dist-info/RECORD
