Metadata-Version: 2.1
Name: datasette-init
Version: 0.2
Summary: Ensure specific tables and views exist on startup
Home-page: https://github.com/simonw/datasette-init
Author: Simon Willison
License: Apache License, Version 2.0
Project-URL: Issues, https://github.com/simonw/datasette-init/issues
Project-URL: CI, https://github.com/simonw/datasette-init/actions
Project-URL: Changelog, https://github.com/simonw/datasette-init/releases
Platform: UNKNOWN
Requires-Dist: datasette (>=0.45)
Requires-Dist: sqlite-utils
Provides-Extra: test
Requires-Dist: pytest ; extra == 'test'
Requires-Dist: pytest-asyncio ; extra == 'test'
Requires-Dist: httpx ; extra == 'test'
